LICENSE
MANIFEST.in
README.md
setup.cfg
setup.py
bype/__init__.py
bype/core.py
bype.egg-info/PKG-INFO
bype.egg-info/SOURCES.txt
bype.egg-info/dependency_links.txt
bype.egg-info/top_level.txt
test/__init__.py
test/test_core.py