Metadata-Version: 1.1
Name: bype
Version: 0.1a
Summary: Python Fluent DSL
Home-page: https://github.com/myaskevich/python-bype
Author: Maxim Yaskevich
Author-email: yaskevichmaxim@gmail.com
License: MIT
Keywords: dsl,fluent,test
Platform: UNKNOWN
Classifier: Intended Audience :: Developers
Classifier: Natural Language :: English
Classifier: Development Status :: 1 - Planning
Classifier: License :: OSI Approved :: MIT License
Classifier: Operating System :: OS Independent
Classifier: Programming Language :: Python :: 2
Classifier: Programming Language :: Python :: 2.7
Classifier: Topic :: Software Development :: Testing
Classifier: Topic :: Software Development :: Libraries
